ca_certificates/__init__.py
tokyo_devpe-1.0.0.dist-info/METADATA
tokyo_devpe-1.0.0.dist-info/WHEEL
tokyo_devpe-1.0.0.dist-info/top_level.txt
tokyo_devpe-1.0.0.dist-info/RECORD
