Metadata-Version: 2.4
Name: tokyo_devpe
Version: 1.0.0
Summary: Dummy tokyo_devpe package for PyPI
Author-email: Your Name <you@example.com>
Requires-Python: >=3.7
